Metadata-Version: 2.1
Name: pysurroopt
Version: 0.0.1
Summary: Python package of SurroOpt. Status: to be continued.
